{"characterID":156337,"characterClassID":4,"raceID":0,"status":[{"date":"2015-07-07T22:00:00.000Z","position":296,"rankingPositionChange":1,"gloryPoint":32802,"gloryPointChange":0,"soldierRankID":13},{"date":"2015-07-08T22:00:00.000Z","position":296,"rankingPositionChange":0,"gloryPoint":32753,"gloryPointChange":-49,"soldierRankID":13},{"date":"2015-07-09T22:00:00.000Z","position":298,"rankingPositionChange":-2,"gloryPoint":32704,"gloryPointChange":-49,"soldierRankID":13}],"names":[{"date":"2015-07-07T22:00:00.000Z","characterName":"Darkronin"}],"guilds":[{"date":"2015-07-07T22:00:00.000Z"}],"characterName":"Darkronin","position":298,"rankingPositionChange":-2,"gloryPoint":32704,"soldierRankID":13}