{
 "characterID": 1023614,
 "characterClassID": 10,
 "raceID": 1,
 "position": 316,
 "rankingPositionChange": 1,
 "gloryPoint": 21555,
 "gloryPointChange": -56,
 "soldierRankID": 12,
 "characterName": "Auroya",
 "status": [
  {
   "date": "2015-08-10T22:00:00.000Z",
   "position": 291,
   "rankingPositionChange": 0,
   "gloryPoint": 22479,
   "gloryPointChange": 0,
   "soldierRankID": 13
  },
  {
   "date": "2015-08-11T22:00:00.000Z",
   "position": 291,
   "rankingPositionChange": 0,
   "gloryPoint": 22479,
   "gloryPointChange": 0,
   "soldierRankID": 13
  },
  {
   "date": "2015-08-12T22:00:00.000Z",
   "position": 296,
   "rankingPositionChange": -5,
   "gloryPoint": 22381,
   "gloryPointChange": -98,
   "soldierRankID": 13
  },
  {
   "date": "2015-08-13T22:00:00.000Z",
   "position": 298,
   "rankingPositionChange": -2,
   "gloryPoint": 22332,
   "gloryPointChange": -49,
   "soldierRankID": 13
  },
  {
   "date": "2015-08-14T22:00:00.000Z",
   "position": 301,
   "rankingPositionChange": -3,
   "gloryPoint": 22283,
   "gloryPointChange": -49,
   "soldierRankID": 12
  },
  {
   "date": "2015-08-15T22:00:00.000Z",
   "position": 301,
   "rankingPositionChange": 0,
   "gloryPoint": 22283,
   "gloryPointChange": 0,
   "soldierRankID": 12
  },
  {
   "date": "2015-08-16T22:00:00.000Z",
   "position": 303,
   "rankingPositionChange": -2,
   "gloryPoint": 22255,
   "gloryPointChange": -28,
   "soldierRankID": 12
  },
  {
   "date": "2015-08-17T22:00:00.000Z",
   "position": 306,
   "rankingPositionChange": -3,
   "gloryPoint": 22227,
   "gloryPointChange": -28,
   "soldierRankID": 12
  },
  {
   "date": "2015-08-18T22:00:00.000Z",
   "position": 308,
   "rankingPositionChange": -2,
   "gloryPoint": 22171,
   "gloryPointChange": -56,
   "soldierRankID": 12
  },
  {
   "date": "2015-08-19T22:00:00.000Z",
   "position": 308,
   "rankingPositionChange": 0,
   "gloryPoint": 22143,
   "gloryPointChange": -28,
   "soldierRankID": 12
  },
  {
   "date": "2015-08-20T22:00:00.000Z",
   "position": 307,
   "rankingPositionChange": 1,
   "gloryPoint": 22115,
   "gloryPointChange": -28,
   "soldierRankID": 12
  },
  {
   "date": "2015-08-21T22:00:00.000Z",
   "position": 308,
   "rankingPositionChange": -1,
   "gloryPoint": 22087,
   "gloryPointChange": -28,
   "soldierRankID": 12
  },
  {
   "date": "2015-08-22T22:00:00.000Z",
   "position": 309,
   "rankingPositionChange": -1,
   "gloryPoint": 22059,
   "gloryPointChange": -28,
   "soldierRankID": 12
  },
  {
   "date": "2015-08-23T22:00:00.000Z",
   "position": 309,
   "rankingPositionChange": 0,
   "gloryPoint": 22031,
   "gloryPointChange": -28,
   "soldierRankID": 12
  },
  {
   "date": "2015-08-25T22:00:00.000Z",
   "position": 309,
   "rankingPositionChange": 0,
   "gloryPoint": 21975,
   "gloryPointChange": -56,
   "soldierRankID": 12
  },
  {
   "date": "2015-08-26T22:00:00.000Z",
   "position": 308,
   "rankingPositionChange": 1,
   "gloryPoint": 21919,
   "gloryPointChange": -56,
   "soldierRankID": 12
  },
  {
   "date": "2015-08-27T22:00:00.000Z",
   "position": 308,
   "rankingPositionChange": 0,
   "gloryPoint": 21891,
   "gloryPointChange": -28,
   "soldierRankID": 12
  },
  {
   "date": "2015-08-28T22:00:00.000Z",
   "position": 309,
   "rankingPositionChange": -1,
   "gloryPoint": 21863,
   "gloryPointChange": -28,
   "soldierRankID": 12
  },
  {
   "date": "2015-08-29T22:00:00.000Z",
   "position": 312,
   "rankingPositionChange": -3,
   "gloryPoint": 21835,
   "gloryPointChange": -28,
   "soldierRankID": 12
  },
  {
   "date": "2015-08-30T22:00:00.000Z",
   "position": 313,
   "rankingPositionChange": -1,
   "gloryPoint": 21807,
   "gloryPointChange": -28,
   "soldierRankID": 12
  },
  {
   "date": "2015-09-01T22:00:00.000Z",
   "position": 319,
   "rankingPositionChange": -6,
   "gloryPoint": 21723,
   "gloryPointChange": -84,
   "soldierRankID": 12
  },
  {
   "date": "2015-09-02T22:00:00.000Z",
   "position": 319,
   "rankingPositionChange": 0,
   "gloryPoint": 21695,
   "gloryPointChange": -28,
   "soldierRankID": 12
  },
  {
   "date": "2015-09-03T22:00:00.000Z",
   "position": 316,
   "rankingPositionChange": 3,
   "gloryPoint": 21667,
   "gloryPointChange": -28,
   "soldierRankID": 12
  },
  {
   "date": "2015-09-04T22:00:00.000Z",
   "position": 317,
   "rankingPositionChange": -1,
   "gloryPoint": 21639,
   "gloryPointChange": -28,
   "soldierRankID": 12
  },
  {
   "date": "2015-09-05T22:00:00.000Z",
   "position": 317,
   "rankingPositionChange": 0,
   "gloryPoint": 21611,
   "gloryPointChange": -28,
   "soldierRankID": 12
  },
  {
   "date": "2015-09-07T22:00:00.000Z",
   "position": 316,
   "rankingPositionChange": 1,
   "gloryPoint": 21555,
   "gloryPointChange": -56,
   "soldierRankID": 12
  }
 ],
 "names": [
  {
   "date": "2015-08-10T22:00:00.000Z",
   "characterName": "Auroya"
  }
 ],
 "guilds": [
  {
   "date": "2015-08-10T22:00:00.000Z"
  }
 ]
}