{"characterID":1293004,"characterClassID":13,"raceID":1,"status":[{"date":"2015-07-07T22:00:00.000Z","position":142,"rankingPositionChange":0,"gloryPoint":42103,"gloryPointChange":0,"soldierRankID":13},{"date":"2015-07-08T22:00:00.000Z","position":144,"rankingPositionChange":-2,"gloryPoint":42054,"gloryPointChange":-49,"soldierRankID":13},{"date":"2015-07-09T22:00:00.000Z","position":144,"rankingPositionChange":0,"gloryPoint":42005,"gloryPointChange":-49,"soldierRankID":13},{"date":"2015-07-10T22:00:00.000Z","position":144,"rankingPositionChange":0,"gloryPoint":41956,"gloryPointChange":-49,"soldierRankID":13},{"date":"2015-07-11T22:00:00.000Z","position":145,"rankingPositionChange":-1,"gloryPoint":41907,"gloryPointChange":-49,"soldierRankID":13},{"date":"2015-07-13T22:00:00.000Z","position":148,"rankingPositionChange":-4,"gloryPoint":41809,"gloryPointChange":-98,"soldierRankID":13},{"date":"2015-07-14T22:00:00.000Z","position":149,"rankingPositionChange":-1,"gloryPoint":41760,"gloryPointChange":-49,"soldierRankID":13},{"date":"2015-07-15T22:00:00.000Z","position":150,"rankingPositionChange":-1,"gloryPoint":41711,"gloryPointChange":-49,"soldierRankID":13},{"date":"2015-07-16T22:00:00.000Z","position":149,"rankingPositionChange":1,"gloryPoint":41662,"gloryPointChange":-49,"soldierRankID":13},{"date":"2015-07-17T22:00:00.000Z","position":150,"rankingPositionChange":-1,"gloryPoint":41613,"gloryPointChange":-49,"soldierRankID":13},{"date":"2015-07-18T22:00:00.000Z","position":152,"rankingPositionChange":-2,"gloryPoint":41564,"gloryPointChange":-49,"soldierRankID":13},{"date":"2015-07-19T22:00:00.000Z","position":152,"rankingPositionChange":0,"gloryPoint":41515,"gloryPointChange":-49,"soldierRankID":13},{"date":"2015-07-20T22:00:00.000Z","position":152,"rankingPositionChange":0,"gloryPoint":41466,"gloryPointChange":-49,"soldierRankID":13},{"date":"2015-07-21T22:00:00.000Z","position":152,"rankingPositionChange":0,"gloryPoint":41368,"gloryPointChange":-98,"soldierRankID":13},{"date":"2015-07-22T22:00:00.000Z","position":152,"rankingPositionChange":0,"gloryPoint":41319,"gloryPointChange":-49,"soldierRankID":13}],"names":[{"date":"2015-07-07T22:00:00.000Z","characterName":"Robotopoulo"}],"guilds":[{"date":"2015-07-07T22:00:00.000Z","guildName":"The Guardians","guildID":10840}],"characterName":"Robotopoulo","guildName":"The Guardians","guildID":10840,"position":152,"rankingPositionChange":0,"gloryPoint":41319,"soldierRankID":13}