{"characterID":42092,"characterClassID":10,"raceID":1,"status":[{"date":"2015-07-07T22:00:00.000Z","position":26,"rankingPositionChange":0,"gloryPoint":145273,"gloryPointChange":0,"soldierRankID":15},{"date":"2015-07-08T22:00:00.000Z","position":26,"rankingPositionChange":0,"gloryPoint":145154,"gloryPointChange":-119,"soldierRankID":15},{"date":"2015-07-09T22:00:00.000Z","position":26,"rankingPositionChange":0,"gloryPoint":145035,"gloryPointChange":-119,"soldierRankID":15},{"date":"2015-07-10T22:00:00.000Z","position":26,"rankingPositionChange":0,"gloryPoint":145566,"gloryPointChange":531,"soldierRankID":15},{"date":"2015-07-11T22:00:00.000Z","position":26,"rankingPositionChange":0,"gloryPoint":145447,"gloryPointChange":-119,"soldierRankID":15},{"date":"2015-07-13T22:00:00.000Z","position":26,"rankingPositionChange":0,"gloryPoint":145862,"gloryPointChange":415,"soldierRankID":15},{"date":"2015-07-14T22:00:00.000Z","position":26,"rankingPositionChange":0,"gloryPoint":146451,"gloryPointChange":589,"soldierRankID":15},{"date":"2015-07-15T22:00:00.000Z","position":26,"rankingPositionChange":0,"gloryPoint":146332,"gloryPointChange":-119,"soldierRankID":15},{"date":"2015-07-16T22:00:00.000Z","position":26,"rankingPositionChange":0,"gloryPoint":146213,"gloryPointChange":-119,"soldierRankID":15},{"date":"2015-07-17T22:00:00.000Z","position":26,"rankingPositionChange":0,"gloryPoint":146094,"gloryPointChange":-119,"soldierRankID":15},{"date":"2015-07-18T22:00:00.000Z","position":26,"rankingPositionChange":0,"gloryPoint":145975,"gloryPointChange":-119,"soldierRankID":15},{"date":"2015-07-19T22:00:00.000Z","position":27,"rankingPositionChange":-1,"gloryPoint":145856,"gloryPointChange":-119,"soldierRankID":15},{"date":"2015-07-20T22:00:00.000Z","position":27,"rankingPositionChange":0,"gloryPoint":146192,"gloryPointChange":336,"soldierRankID":15},{"date":"2015-07-21T22:00:00.000Z","position":27,"rankingPositionChange":0,"gloryPoint":145954,"gloryPointChange":-238,"soldierRankID":15},{"date":"2015-07-22T22:00:00.000Z","position":28,"rankingPositionChange":-1,"gloryPoint":145835,"gloryPointChange":-119,"soldierRankID":15},{"date":"2015-07-23T22:00:00.000Z","position":28,"rankingPositionChange":0,"gloryPoint":145597,"gloryPointChange":-238,"soldierRankID":15},{"date":"2015-07-24T22:00:00.000Z","position":28,"rankingPositionChange":0,"gloryPoint":145571,"gloryPointChange":-26,"soldierRankID":15},{"date":"2015-07-25T22:00:00.000Z","position":28,"rankingPositionChange":0,"gloryPoint":145452,"gloryPointChange":-119,"soldierRankID":15},{"date":"2015-07-27T22:00:00.000Z","position":28,"rankingPositionChange":0,"gloryPoint":145230,"gloryPointChange":-222,"soldierRankID":15},{"date":"2015-07-28T22:00:00.000Z","position":28,"rankingPositionChange":0,"gloryPoint":145111,"gloryPointChange":-119,"soldierRankID":15},{"date":"2015-07-29T22:00:00.000Z","position":28,"rankingPositionChange":0,"gloryPoint":145092,"gloryPointChange":-19,"soldierRankID":15},{"date":"2015-07-30T22:00:00.000Z","position":28,"rankingPositionChange":0,"gloryPoint":144973,"gloryPointChange":-119,"soldierRankID":15},{"date":"2015-07-31T22:00:00.000Z","position":28,"rankingPositionChange":0,"gloryPoint":145154,"gloryPointChange":181,"soldierRankID":15},{"date":"2015-08-01T22:00:00.000Z","position":28,"rankingPositionChange":0,"gloryPoint":145113,"gloryPointChange":-41,"soldierRankID":15},{"date":"2015-08-02T22:00:00.000Z","position":28,"rankingPositionChange":0,"gloryPoint":145122,"gloryPointChange":9,"soldierRankID":15},{"date":"2015-08-03T22:00:00.000Z","position":28,"rankingPositionChange":0,"gloryPoint":145640,"gloryPointChange":518,"soldierRankID":15},{"date":"2015-08-04T22:00:00.000Z","position":28,"rankingPositionChange":0,"gloryPoint":145871,"gloryPointChange":231,"soldierRankID":15},{"date":"2015-08-05T22:00:00.000Z","position":28,"rankingPositionChange":0,"gloryPoint":145752,"gloryPointChange":-119,"soldierRankID":15},{"date":"2015-08-06T22:00:00.000Z","position":28,"rankingPositionChange":0,"gloryPoint":145633,"gloryPointChange":-119,"soldierRankID":15},{"date":"2015-08-07T22:00:00.000Z","position":28,"rankingPositionChange":0,"gloryPoint":145514,"gloryPointChange":-119,"soldierRankID":15},{"date":"2015-08-08T22:00:00.000Z","position":28,"rankingPositionChange":0,"gloryPoint":145514,"gloryPointChange":0,"soldierRankID":15},{"date":"2015-08-09T22:00:00.000Z","position":28,"rankingPositionChange":0,"gloryPoint":145395,"gloryPointChange":-119,"soldierRankID":15},{"date":"2015-08-10T22:00:00.000Z","position":28,"rankingPositionChange":0,"gloryPoint":145327,"gloryPointChange":-68,"soldierRankID":15}],"names":[{"date":"2015-07-07T22:00:00.000Z","characterName":"Xelina"}],"guilds":[{"date":"2015-07-07T22:00:00.000Z","guildName":"ReKt","guildID":5490}],"characterName":"Xelina","guildName":"ReKt","guildID":5490,"position":28,"rankingPositionChange":0,"gloryPoint":145327,"soldierRankID":15}