{"characterID":430311,"characterClassID":8,"raceID":1,"status":[{"date":"2015-07-07T22:00:00.000Z","position":195,"rankingPositionChange":0,"gloryPoint":21340,"gloryPointChange":0,"soldierRankID":13},{"date":"2015-07-08T22:00:00.000Z","position":195,"rankingPositionChange":0,"gloryPoint":21291,"gloryPointChange":-49,"soldierRankID":13},{"date":"2015-07-09T22:00:00.000Z","position":196,"rankingPositionChange":-1,"gloryPoint":21242,"gloryPointChange":-49,"soldierRankID":13},{"date":"2015-07-10T22:00:00.000Z","position":198,"rankingPositionChange":-2,"gloryPoint":21193,"gloryPointChange":-49,"soldierRankID":13},{"date":"2015-07-11T22:00:00.000Z","position":198,"rankingPositionChange":0,"gloryPoint":21276,"gloryPointChange":83,"soldierRankID":13},{"date":"2015-07-13T22:00:00.000Z","position":199,"rankingPositionChange":-1,"gloryPoint":21306,"gloryPointChange":30,"soldierRankID":13},{"date":"2015-07-14T22:00:00.000Z","position":199,"rankingPositionChange":0,"gloryPoint":21362,"gloryPointChange":56,"soldierRankID":13},{"date":"2015-07-15T22:00:00.000Z","position":199,"rankingPositionChange":0,"gloryPoint":21313,"gloryPointChange":-49,"soldierRankID":13},{"date":"2015-07-16T22:00:00.000Z","position":198,"rankingPositionChange":1,"gloryPoint":21264,"gloryPointChange":-49,"soldierRankID":13},{"date":"2015-07-17T22:00:00.000Z","position":198,"rankingPositionChange":0,"gloryPoint":21215,"gloryPointChange":-49,"soldierRankID":13},{"date":"2015-07-18T22:00:00.000Z","position":197,"rankingPositionChange":1,"gloryPoint":21166,"gloryPointChange":-49,"soldierRankID":13},{"date":"2015-07-19T22:00:00.000Z","position":197,"rankingPositionChange":0,"gloryPoint":21117,"gloryPointChange":-49,"soldierRankID":13},{"date":"2015-07-20T22:00:00.000Z","position":198,"rankingPositionChange":-1,"gloryPoint":21068,"gloryPointChange":-49,"soldierRankID":13},{"date":"2015-07-21T22:00:00.000Z","position":198,"rankingPositionChange":0,"gloryPoint":20970,"gloryPointChange":-98,"soldierRankID":13},{"date":"2015-07-22T22:00:00.000Z","position":200,"rankingPositionChange":-2,"gloryPoint":20921,"gloryPointChange":-49,"soldierRankID":13},{"date":"2015-07-23T22:00:00.000Z","position":200,"rankingPositionChange":0,"gloryPoint":20823,"gloryPointChange":-98,"soldierRankID":13},{"date":"2015-07-24T22:00:00.000Z","position":201,"rankingPositionChange":-1,"gloryPoint":20784,"gloryPointChange":-39,"soldierRankID":13},{"date":"2015-07-25T22:00:00.000Z","position":201,"rankingPositionChange":0,"gloryPoint":20846,"gloryPointChange":62,"soldierRankID":13},{"date":"2015-07-27T22:00:00.000Z","position":202,"rankingPositionChange":-1,"gloryPoint":20748,"gloryPointChange":-98,"soldierRankID":13},{"date":"2015-07-28T22:00:00.000Z","position":201,"rankingPositionChange":1,"gloryPoint":20699,"gloryPointChange":-49,"soldierRankID":13},{"date":"2015-07-29T22:00:00.000Z","position":199,"rankingPositionChange":2,"gloryPoint":20835,"gloryPointChange":136,"soldierRankID":13}],"names":[{"date":"2015-07-07T22:00:00.000Z","characterName":"Tynion"}],"guilds":[{"date":"2015-07-07T22:00:00.000Z","guildName":"Maligne","guildID":13523}],"characterName":"Tynion","guildName":"Maligne","guildID":13523,"position":199,"rankingPositionChange":2,"gloryPoint":20835,"soldierRankID":13}