{"characterID":551374,"characterClassID":10,"raceID":1,"status":[{"date":"2015-07-17T22:00:00.000Z","position":987,"rankingPositionChange":0,"gloryPoint":5034,"gloryPointChange":0,"soldierRankID":10},{"date":"2015-07-18T22:00:00.000Z","position":973,"rankingPositionChange":14,"gloryPoint":5233,"gloryPointChange":199,"soldierRankID":10},{"date":"2015-07-19T22:00:00.000Z","position":953,"rankingPositionChange":20,"gloryPoint":5354,"gloryPointChange":121,"soldierRankID":10},{"date":"2015-07-20T22:00:00.000Z","position":953,"rankingPositionChange":20,"gloryPoint":5354,"gloryPointChange":0,"soldierRankID":10}],"names":[{"date":"2015-07-17T22:00:00.000Z","characterName":"Aroamatyne"}],"guilds":[{"date":"2015-07-17T22:00:00.000Z","guildName":"xUtopiax","guildID":14207}],"characterName":"Aroamatyne","guildName":"xUtopiax","guildID":14207,"position":953,"rankingPositionChange":20,"gloryPoint":5354,"soldierRankID":10}