{"characterID":552362,"characterClassID":2,"raceID":0,"status":[{"date":"2015-07-07T22:00:00.000Z","position":27,"rankingPositionChange":0,"gloryPoint":187301,"gloryPointChange":0,"soldierRankID":15},{"date":"2015-07-08T22:00:00.000Z","position":27,"rankingPositionChange":0,"gloryPoint":187920,"gloryPointChange":619,"soldierRankID":15},{"date":"2015-07-09T22:00:00.000Z","position":27,"rankingPositionChange":0,"gloryPoint":188358,"gloryPointChange":438,"soldierRankID":15},{"date":"2015-07-10T22:00:00.000Z","position":27,"rankingPositionChange":0,"gloryPoint":188739,"gloryPointChange":381,"soldierRankID":15},{"date":"2015-07-11T22:00:00.000Z","position":27,"rankingPositionChange":0,"gloryPoint":189029,"gloryPointChange":290,"soldierRankID":15},{"date":"2015-07-13T22:00:00.000Z","position":26,"rankingPositionChange":1,"gloryPoint":189954,"gloryPointChange":925,"soldierRankID":15},{"date":"2015-07-14T22:00:00.000Z","position":26,"rankingPositionChange":0,"gloryPoint":190633,"gloryPointChange":679,"soldierRankID":15},{"date":"2015-07-15T22:00:00.000Z","position":26,"rankingPositionChange":0,"gloryPoint":191206,"gloryPointChange":573,"soldierRankID":15},{"date":"2015-07-16T22:00:00.000Z","position":26,"rankingPositionChange":0,"gloryPoint":191879,"gloryPointChange":673,"soldierRankID":15},{"date":"2015-07-17T22:00:00.000Z","position":26,"rankingPositionChange":0,"gloryPoint":192466,"gloryPointChange":587,"soldierRankID":15},{"date":"2015-07-18T22:00:00.000Z","position":26,"rankingPositionChange":0,"gloryPoint":193277,"gloryPointChange":811,"soldierRankID":15},{"date":"2015-07-19T22:00:00.000Z","position":26,"rankingPositionChange":0,"gloryPoint":193549,"gloryPointChange":272,"soldierRankID":15},{"date":"2015-07-20T22:00:00.000Z","position":26,"rankingPositionChange":0,"gloryPoint":193990,"gloryPointChange":441,"soldierRankID":15},{"date":"2015-07-21T22:00:00.000Z","position":26,"rankingPositionChange":0,"gloryPoint":194562,"gloryPointChange":572,"soldierRankID":15},{"date":"2015-07-22T22:00:00.000Z","position":26,"rankingPositionChange":0,"gloryPoint":195177,"gloryPointChange":615,"soldierRankID":15},{"date":"2015-07-23T22:00:00.000Z","position":26,"rankingPositionChange":0,"gloryPoint":195748,"gloryPointChange":571,"soldierRankID":15},{"date":"2015-07-24T22:00:00.000Z","position":26,"rankingPositionChange":0,"gloryPoint":196552,"gloryPointChange":804,"soldierRankID":15},{"date":"2015-07-25T22:00:00.000Z","position":26,"rankingPositionChange":0,"gloryPoint":197032,"gloryPointChange":480,"soldierRankID":15},{"date":"2015-07-26T22:00:00.000Z","position":26,"rankingPositionChange":0,"gloryPoint":197341,"gloryPointChange":309,"soldierRankID":15},{"date":"2015-07-27T22:00:00.000Z","position":26,"rankingPositionChange":0,"gloryPoint":198034,"gloryPointChange":693,"soldierRankID":15},{"date":"2015-07-28T22:00:00.000Z","position":25,"rankingPositionChange":1,"gloryPoint":198587,"gloryPointChange":553,"soldierRankID":15},{"date":"2015-07-29T22:00:00.000Z","position":25,"rankingPositionChange":0,"gloryPoint":199326,"gloryPointChange":739,"soldierRankID":15},{"date":"2015-07-30T22:00:00.000Z","position":25,"rankingPositionChange":0,"gloryPoint":200092,"gloryPointChange":766,"soldierRankID":15},{"date":"2015-07-31T22:00:00.000Z","position":24,"rankingPositionChange":1,"gloryPoint":200683,"gloryPointChange":591,"soldierRankID":15},{"date":"2015-08-01T22:00:00.000Z","position":24,"rankingPositionChange":0,"gloryPoint":201011,"gloryPointChange":328,"soldierRankID":15}],"names":[{"date":"2015-07-07T22:00:00.000Z","characterName":"Furen"}],"guilds":[{"date":"2015-07-07T22:00:00.000Z","guildName":"OUTLAWS","guildID":4233}],"characterName":"Furen","guildName":"OUTLAWS","guildID":4233,"position":24,"rankingPositionChange":0,"gloryPoint":201011,"soldierRankID":15}