{"characterID":682326,"characterClassID":11,"raceID":0,"status":[{"date":"2015-07-07T22:00:00.000Z","position":450,"rankingPositionChange":0,"gloryPoint":18157,"gloryPointChange":0,"soldierRankID":12},{"date":"2015-07-08T22:00:00.000Z","position":450,"rankingPositionChange":0,"gloryPoint":18238,"gloryPointChange":81,"soldierRankID":12},{"date":"2015-07-09T22:00:00.000Z","position":437,"rankingPositionChange":13,"gloryPoint":18842,"gloryPointChange":604,"soldierRankID":12},{"date":"2015-07-10T22:00:00.000Z","position":434,"rankingPositionChange":3,"gloryPoint":19012,"gloryPointChange":170,"soldierRankID":12},{"date":"2015-07-11T22:00:00.000Z","position":438,"rankingPositionChange":-4,"gloryPoint":18984,"gloryPointChange":-28,"soldierRankID":12},{"date":"2015-07-13T22:00:00.000Z","position":426,"rankingPositionChange":12,"gloryPoint":20170,"gloryPointChange":1186,"soldierRankID":12},{"date":"2015-07-14T22:00:00.000Z","position":429,"rankingPositionChange":-3,"gloryPoint":20142,"gloryPointChange":-28,"soldierRankID":12},{"date":"2015-07-15T22:00:00.000Z","position":431,"rankingPositionChange":-2,"gloryPoint":20114,"gloryPointChange":-28,"soldierRankID":12},{"date":"2015-07-16T22:00:00.000Z","position":432,"rankingPositionChange":-1,"gloryPoint":20086,"gloryPointChange":-28,"soldierRankID":12},{"date":"2015-07-17T22:00:00.000Z","position":431,"rankingPositionChange":1,"gloryPoint":20058,"gloryPointChange":-28,"soldierRankID":12},{"date":"2015-07-18T22:00:00.000Z","position":434,"rankingPositionChange":-3,"gloryPoint":20030,"gloryPointChange":-28,"soldierRankID":12},{"date":"2015-07-19T22:00:00.000Z","position":434,"rankingPositionChange":0,"gloryPoint":20002,"gloryPointChange":-28,"soldierRankID":12},{"date":"2015-07-20T22:00:00.000Z","position":434,"rankingPositionChange":0,"gloryPoint":20002,"gloryPointChange":0,"soldierRankID":12}],"names":[{"date":"2015-07-07T22:00:00.000Z","characterName":"Horriii"}],"guilds":[{"date":"2015-07-07T22:00:00.000Z"},{"date":"2015-07-09T22:00:00.000Z","guildName":"Messenger Of Violence MOV","guildID":1335},{"date":"2015-07-14T22:00:00.000Z"}],"characterName":"Horriii","position":434,"rankingPositionChange":0,"gloryPoint":20002,"soldierRankID":12}