{"characterID":1217619,"characterClassID":2,"raceID":1,"status":[{"date":"2015-07-07T22:00:00.000Z","position":912,"rankingPositionChange":1,"gloryPoint":4585,"gloryPointChange":0,"soldierRankID":10},{"date":"2015-07-08T22:00:00.000Z","position":909,"rankingPositionChange":3,"gloryPoint":4640,"gloryPointChange":55,"soldierRankID":10},{"date":"2015-07-09T22:00:00.000Z","position":912,"rankingPositionChange":-3,"gloryPoint":4633,"gloryPointChange":-7,"soldierRankID":10},{"date":"2015-07-10T22:00:00.000Z","position":915,"rankingPositionChange":-3,"gloryPoint":4626,"gloryPointChange":-7,"soldierRankID":10},{"date":"2015-07-11T22:00:00.000Z","position":900,"rankingPositionChange":15,"gloryPoint":4759,"gloryPointChange":133,"soldierRankID":10},{"date":"2015-07-13T22:00:00.000Z","position":899,"rankingPositionChange":1,"gloryPoint":4773,"gloryPointChange":14,"soldierRankID":10},{"date":"2015-07-14T22:00:00.000Z","position":904,"rankingPositionChange":-5,"gloryPoint":4766,"gloryPointChange":-7,"soldierRankID":10},{"date":"2015-07-15T22:00:00.000Z","position":902,"rankingPositionChange":2,"gloryPoint":4759,"gloryPointChange":-7,"soldierRankID":10},{"date":"2015-07-16T22:00:00.000Z","position":906,"rankingPositionChange":-4,"gloryPoint":4752,"gloryPointChange":-7,"soldierRankID":10},{"date":"2015-07-17T22:00:00.000Z","position":907,"rankingPositionChange":-1,"gloryPoint":4745,"gloryPointChange":-7,"soldierRankID":10},{"date":"2015-07-18T22:00:00.000Z","position":898,"rankingPositionChange":9,"gloryPoint":4816,"gloryPointChange":71,"soldierRankID":10},{"date":"2015-07-19T22:00:00.000Z","position":900,"rankingPositionChange":-2,"gloryPoint":4809,"gloryPointChange":-7,"soldierRankID":10},{"date":"2015-07-20T22:00:00.000Z","position":899,"rankingPositionChange":1,"gloryPoint":4830,"gloryPointChange":21,"soldierRankID":10},{"date":"2015-07-21T22:00:00.000Z","position":897,"rankingPositionChange":2,"gloryPoint":4816,"gloryPointChange":-14,"soldierRankID":10},{"date":"2015-07-22T22:00:00.000Z","position":902,"rankingPositionChange":-5,"gloryPoint":4809,"gloryPointChange":-7,"soldierRankID":10},{"date":"2015-07-23T22:00:00.000Z","position":905,"rankingPositionChange":-3,"gloryPoint":4795,"gloryPointChange":-14,"soldierRankID":10},{"date":"2015-07-24T22:00:00.000Z","position":906,"rankingPositionChange":-1,"gloryPoint":4788,"gloryPointChange":-7,"soldierRankID":10},{"date":"2015-07-25T22:00:00.000Z","position":911,"rankingPositionChange":-5,"gloryPoint":4781,"gloryPointChange":-7,"soldierRankID":10},{"date":"2015-07-27T22:00:00.000Z","position":904,"rankingPositionChange":7,"gloryPoint":4991,"gloryPointChange":210,"soldierRankID":10},{"date":"2015-07-28T22:00:00.000Z","position":902,"rankingPositionChange":2,"gloryPoint":5072,"gloryPointChange":81,"soldierRankID":10},{"date":"2015-07-29T22:00:00.000Z","position":896,"rankingPositionChange":6,"gloryPoint":5186,"gloryPointChange":114,"soldierRankID":10},{"date":"2015-07-30T22:00:00.000Z","position":895,"rankingPositionChange":1,"gloryPoint":5251,"gloryPointChange":65,"soldierRankID":10},{"date":"2015-07-31T22:00:00.000Z","position":898,"rankingPositionChange":-3,"gloryPoint":5244,"gloryPointChange":-7,"soldierRankID":10},{"date":"2015-08-01T22:00:00.000Z","position":901,"rankingPositionChange":-3,"gloryPoint":5237,"gloryPointChange":-7,"soldierRankID":10},{"date":"2015-08-02T22:00:00.000Z","position":900,"rankingPositionChange":1,"gloryPoint":5230,"gloryPointChange":-7,"soldierRankID":10},{"date":"2015-08-03T22:00:00.000Z","position":896,"rankingPositionChange":4,"gloryPoint":5277,"gloryPointChange":47,"soldierRankID":10},{"date":"2015-08-04T22:00:00.000Z","position":894,"rankingPositionChange":2,"gloryPoint":5328,"gloryPointChange":51,"soldierRankID":10},{"date":"2015-08-05T22:00:00.000Z","position":881,"rankingPositionChange":13,"gloryPoint":5443,"gloryPointChange":115,"soldierRankID":10},{"date":"2015-08-06T22:00:00.000Z","position":881,"rankingPositionChange":0,"gloryPoint":5464,"gloryPointChange":21,"soldierRankID":10},{"date":"2015-08-07T22:00:00.000Z","position":884,"rankingPositionChange":-3,"gloryPoint":5457,"gloryPointChange":-7,"soldierRankID":10}],"names":[{"date":"2015-07-07T22:00:00.000Z","characterName":"Guardians"}],"guilds":[{"date":"2015-07-07T22:00:00.000Z","guildName":"Disorder","guildID":12292}],"characterName":"Guardians","guildName":"Disorder","guildID":12292,"position":884,"rankingPositionChange":-3,"gloryPoint":5457,"soldierRankID":10}