{"characterID":839680,"characterClassID":4,"raceID":1,"status":[{"date":"2015-07-11T22:00:00.000Z","position":980,"rankingPositionChange":0,"gloryPoint":4131,"gloryPointChange":0,"soldierRankID":10},{"date":"2015-07-13T22:00:00.000Z","position":880,"rankingPositionChange":100,"gloryPoint":5036,"gloryPointChange":905,"soldierRankID":10},{"date":"2015-07-14T22:00:00.000Z","position":875,"rankingPositionChange":5,"gloryPoint":5113,"gloryPointChange":77,"soldierRankID":10},{"date":"2015-07-15T22:00:00.000Z","position":850,"rankingPositionChange":25,"gloryPoint":5569,"gloryPointChange":456,"soldierRankID":10},{"date":"2015-07-16T22:00:00.000Z","position":833,"rankingPositionChange":17,"gloryPoint":5978,"gloryPointChange":409,"soldierRankID":10},{"date":"2015-07-17T22:00:00.000Z","position":823,"rankingPositionChange":10,"gloryPoint":6080,"gloryPointChange":102,"soldierRankID":10},{"date":"2015-07-18T22:00:00.000Z","position":810,"rankingPositionChange":13,"gloryPoint":6288,"gloryPointChange":208,"soldierRankID":10},{"date":"2015-07-19T22:00:00.000Z","position":791,"rankingPositionChange":19,"gloryPoint":6525,"gloryPointChange":237,"soldierRankID":10},{"date":"2015-07-20T22:00:00.000Z","position":779,"rankingPositionChange":12,"gloryPoint":6768,"gloryPointChange":243,"soldierRankID":10},{"date":"2015-07-21T22:00:00.000Z","position":771,"rankingPositionChange":8,"gloryPoint":6931,"gloryPointChange":163,"soldierRankID":10},{"date":"2015-07-22T22:00:00.000Z","position":768,"rankingPositionChange":3,"gloryPoint":7002,"gloryPointChange":71,"soldierRankID":10},{"date":"2015-07-23T22:00:00.000Z","position":754,"rankingPositionChange":14,"gloryPoint":7199,"gloryPointChange":197,"soldierRankID":10},{"date":"2015-07-24T22:00:00.000Z","position":751,"rankingPositionChange":3,"gloryPoint":7192,"gloryPointChange":-7,"soldierRankID":10},{"date":"2015-07-25T22:00:00.000Z","position":760,"rankingPositionChange":-9,"gloryPoint":7185,"gloryPointChange":-7,"soldierRankID":10},{"date":"2015-07-27T22:00:00.000Z","position":758,"rankingPositionChange":2,"gloryPoint":7292,"gloryPointChange":107,"soldierRankID":10},{"date":"2015-07-28T22:00:00.000Z","position":752,"rankingPositionChange":6,"gloryPoint":7484,"gloryPointChange":192,"soldierRankID":10},{"date":"2015-07-29T22:00:00.000Z","position":737,"rankingPositionChange":15,"gloryPoint":7863,"gloryPointChange":379,"soldierRankID":10},{"date":"2015-07-30T22:00:00.000Z","position":734,"rankingPositionChange":3,"gloryPoint":7978,"gloryPointChange":115,"soldierRankID":10},{"date":"2015-07-31T22:00:00.000Z","position":732,"rankingPositionChange":2,"gloryPoint":8217,"gloryPointChange":239,"soldierRankID":10},{"date":"2015-08-01T22:00:00.000Z","position":727,"rankingPositionChange":5,"gloryPoint":8408,"gloryPointChange":191,"soldierRankID":10},{"date":"2015-08-02T22:00:00.000Z","position":695,"rankingPositionChange":32,"gloryPoint":9031,"gloryPointChange":623,"soldierRankID":11},{"date":"2015-08-03T22:00:00.000Z","position":677,"rankingPositionChange":18,"gloryPoint":9358,"gloryPointChange":327,"soldierRankID":11},{"date":"2015-08-04T22:00:00.000Z","position":661,"rankingPositionChange":16,"gloryPoint":9686,"gloryPointChange":328,"soldierRankID":11},{"date":"2015-08-05T22:00:00.000Z","position":649,"rankingPositionChange":12,"gloryPoint":9982,"gloryPointChange":296,"soldierRankID":11},{"date":"2015-08-06T22:00:00.000Z","position":630,"rankingPositionChange":19,"gloryPoint":10279,"gloryPointChange":297,"soldierRankID":11},{"date":"2015-08-07T22:00:00.000Z","position":620,"rankingPositionChange":10,"gloryPoint":10540,"gloryPointChange":261,"soldierRankID":11},{"date":"2015-08-08T22:00:00.000Z","position":620,"rankingPositionChange":0,"gloryPoint":10540,"gloryPointChange":0,"soldierRankID":11},{"date":"2015-08-09T22:00:00.000Z","position":612,"rankingPositionChange":8,"gloryPoint":10943,"gloryPointChange":403,"soldierRankID":11},{"date":"2015-08-10T22:00:00.000Z","position":621,"rankingPositionChange":-9,"gloryPoint":10951,"gloryPointChange":8,"soldierRankID":11}],"names":[{"date":"2015-07-11T22:00:00.000Z","characterName":"Ykubi"}],"guilds":[{"date":"2015-07-11T22:00:00.000Z","guildName":"Hit And Run","guildID":36548},{"date":"2015-08-03T22:00:00.000Z","guildName":"Les Faucheurs D  Ames","guildID":26905}],"characterName":"Ykubi","guildName":"Les Faucheurs D  Ames","guildID":26905,"position":621,"rankingPositionChange":-9,"gloryPoint":10951,"soldierRankID":11}