{"characterID":223026,"characterClassID":7,"raceID":1,"status":[{"date":"2015-07-31T22:00:00.000Z","position":172,"rankingPositionChange":1,"gloryPoint":54851,"gloryPointChange":0,"soldierRankID":13},{"date":"2015-08-01T22:00:00.000Z","position":173,"rankingPositionChange":-1,"gloryPoint":55202,"gloryPointChange":351,"soldierRankID":13},{"date":"2015-08-02T22:00:00.000Z","position":172,"rankingPositionChange":1,"gloryPoint":55360,"gloryPointChange":158,"soldierRankID":13},{"date":"2015-08-03T22:00:00.000Z","position":172,"rankingPositionChange":0,"gloryPoint":55434,"gloryPointChange":74,"soldierRankID":13},{"date":"2015-08-04T22:00:00.000Z","position":173,"rankingPositionChange":-1,"gloryPoint":55385,"gloryPointChange":-49,"soldierRankID":13},{"date":"2015-08-05T22:00:00.000Z","position":172,"rankingPositionChange":1,"gloryPoint":55539,"gloryPointChange":154,"soldierRankID":13},{"date":"2015-08-06T22:00:00.000Z","position":171,"rankingPositionChange":1,"gloryPoint":55653,"gloryPointChange":114,"soldierRankID":13},{"date":"2015-08-07T22:00:00.000Z","position":172,"rankingPositionChange":-1,"gloryPoint":55707,"gloryPointChange":54,"soldierRankID":13},{"date":"2015-08-08T22:00:00.000Z","position":172,"rankingPositionChange":0,"gloryPoint":55707,"gloryPointChange":0,"soldierRankID":13},{"date":"2015-08-09T22:00:00.000Z","position":169,"rankingPositionChange":3,"gloryPoint":56211,"gloryPointChange":504,"soldierRankID":13},{"date":"2015-08-10T22:00:00.000Z","position":169,"rankingPositionChange":0,"gloryPoint":56476,"gloryPointChange":265,"soldierRankID":13},{"date":"2015-08-11T22:00:00.000Z","position":169,"rankingPositionChange":0,"gloryPoint":56476,"gloryPointChange":0,"soldierRankID":13},{"date":"2015-08-12T22:00:00.000Z","position":168,"rankingPositionChange":1,"gloryPoint":56724,"gloryPointChange":248,"soldierRankID":13},{"date":"2015-08-13T22:00:00.000Z","position":167,"rankingPositionChange":1,"gloryPoint":56878,"gloryPointChange":154,"soldierRankID":13},{"date":"2015-08-14T22:00:00.000Z","position":167,"rankingPositionChange":0,"gloryPoint":56932,"gloryPointChange":54,"soldierRankID":13},{"date":"2015-08-15T22:00:00.000Z","position":167,"rankingPositionChange":0,"gloryPoint":56932,"gloryPointChange":0,"soldierRankID":13},{"date":"2015-08-16T22:00:00.000Z","position":169,"rankingPositionChange":-2,"gloryPoint":57146,"gloryPointChange":214,"soldierRankID":13},{"date":"2015-08-17T22:00:00.000Z","position":169,"rankingPositionChange":0,"gloryPoint":57160,"gloryPointChange":14,"soldierRankID":13},{"date":"2015-08-18T22:00:00.000Z","position":167,"rankingPositionChange":2,"gloryPoint":57448,"gloryPointChange":288,"soldierRankID":13},{"date":"2015-08-19T22:00:00.000Z","position":167,"rankingPositionChange":0,"gloryPoint":57502,"gloryPointChange":54,"soldierRankID":13},{"date":"2015-08-20T22:00:00.000Z","position":172,"rankingPositionChange":-5,"gloryPoint":57680,"gloryPointChange":178,"soldierRankID":13},{"date":"2015-08-21T22:00:00.000Z","position":171,"rankingPositionChange":1,"gloryPoint":57794,"gloryPointChange":114,"soldierRankID":13},{"date":"2015-08-22T22:00:00.000Z","position":174,"rankingPositionChange":-3,"gloryPoint":57745,"gloryPointChange":-49,"soldierRankID":13},{"date":"2015-08-23T22:00:00.000Z","position":172,"rankingPositionChange":2,"gloryPoint":57972,"gloryPointChange":227,"soldierRankID":13},{"date":"2015-08-25T22:00:00.000Z","position":170,"rankingPositionChange":2,"gloryPoint":58177,"gloryPointChange":205,"soldierRankID":13},{"date":"2015-08-26T22:00:00.000Z","position":171,"rankingPositionChange":-1,"gloryPoint":58248,"gloryPointChange":71,"soldierRankID":13},{"date":"2015-08-27T22:00:00.000Z","position":171,"rankingPositionChange":0,"gloryPoint":58417,"gloryPointChange":169,"soldierRankID":13},{"date":"2015-08-28T22:00:00.000Z","position":169,"rankingPositionChange":2,"gloryPoint":58534,"gloryPointChange":117,"soldierRankID":13},{"date":"2015-08-29T22:00:00.000Z","position":170,"rankingPositionChange":-1,"gloryPoint":58485,"gloryPointChange":-49,"soldierRankID":13},{"date":"2015-08-30T22:00:00.000Z","position":171,"rankingPositionChange":-1,"gloryPoint":58599,"gloryPointChange":114,"soldierRankID":13},{"date":"2015-09-01T22:00:00.000Z","position":168,"rankingPositionChange":3,"gloryPoint":58911,"gloryPointChange":312,"soldierRankID":13},{"date":"2015-09-02T22:00:00.000Z","position":167,"rankingPositionChange":1,"gloryPoint":59286,"gloryPointChange":375,"soldierRankID":13},{"date":"2015-09-03T22:00:00.000Z","position":167,"rankingPositionChange":0,"gloryPoint":59440,"gloryPointChange":154,"soldierRankID":13}],"names":[{"date":"2015-07-31T22:00:00.000Z","characterName":"Walko"}],"guilds":[{"date":"2015-07-31T22:00:00.000Z","guildName":"Ombre et Lumiere","guildID":8243}],"characterName":"Walko","guildName":"Ombre et Lumiere","guildID":8243,"position":167,"rankingPositionChange":0,"gloryPoint":59440,"soldierRankID":13}